README.md
setup.cfg
setup.py
rnasieve/__init__.py
rnasieve/algo.py
rnasieve/helper.py
rnasieve/model.py
rnasieve/preprocessing.py
rnasieve/stats.py
rnasieve.egg-info/PKG-INFO
rnasieve.egg-info/SOURCES.txt
rnasieve.egg-info/dependency_links.txt
rnasieve.egg-info/requires.txt
rnasieve.egg-info/top_level.txt