Metadata-Version: 2.1
Name: rnasieve
Version: 0.1.2
Summary: A library for the statistical deconvolution of RNA bulk samples with single-cell references.
Home-page: https://github.com/songlab-cal/rna-sieve
Author: Justin Hong
Author-email: justinhong@berkeley.edu
License: GPL
Download-URL: https://github.com/songlab-cal/archive/v_0_1_2.tar.gz
Keywords: rna,deconvolution,statistics,single-cell,proportion,bulk
Platform: UNKNOWN
Classifier: Intended Audience :: Science/Research
Classifier: Topic :: Scientific/Engineering :: Bio-Informatics
Classifier: License :: OSI Approved :: GNU General Public License (GPL)
Classifier: Programming Language :: Python :: 3.5
Classifier: Programming Language :: Python :: 3.6
Classifier: Programming Language :: Python :: 3.7
